{"statuses":[{"metadata":{"iso_language_code":"en","result_type":"recent"},"created_at":"Fri Jun 12 20:32:55 +0000 2015","id":609458378071494656,"id_str":"609458378071494656","text":"RT @Obonjo: Did Rap music do this to you? Did Emiinem, Justin Timberlake and Jusrtin Beiber do this to you.  #askrachel","source":"\u003ca href=\"http:\/\/twitter.com\/download\/iphone\" rel=\"nofollow\"\u003eTwitter for iPhone\u003c\/a\u003e","truncated":false,"in_reply_to_status_id":null,"in_reply_to_status_id_str":null,"in_reply_to_user_id":null,"in_reply_to_user_id_str":null,"in_reply_to_screen_name":null,"user":{"id":373965187,"id_str":"373965187","name":"fenny","screen_name":"heelssopretty","location":"Strawberry Fields","description":"Fun loving,free spirited bird.","url":null,"entities":{"description":{"urls":[]}},"protected":false,"followers_count":87,"friends_count":175,"listed_count":0,"created_at":"Thu Sep 15 13:40:21 +0000 2011","favourites_count":14,"utc_offset":null,"time_zone":null,"geo_enabled":false,"verified":false,"statuses_count":1103,"lang":"en","contributors_enabled":false,"is_translator":false,"is_translation_enabled":false,"profile_background_color":"EBEBEB","profile_background_image_url":"http:\/\/abs.twimg.com\/images\/themes\/theme7\/bg.gif","profile_background_image_url_https":"https:\/\/abs.twimg.com\/images\/themes\/theme7\/bg.gif","profile_background_tile":false,"profile_image_url":"http:\/\/pbs.twimg.com\/profile_images\/458897221367652352\/rMcrGIXp_normal.jpeg","profile_image_url_https":"https:\/\/pbs.twimg.com\/profile_images\/458897221367652352\/rMcrGIXp_normal.jpeg","profile_banner_url":"https:\/\/pbs.twimg.com\/profile_banners\/373965187\/1384928886","profile_link_color":"990000","profile_sidebar_border_color":"DFDFDF","profile_sidebar_fill_color":"F3F3F3","profile_text_color":"333333","profile_use_background_image":true,"default_profile":false,"default_profile_image":false,"following":null,"follow_request_sent":null,"notifications":null},"geo":null,"coordinates":null,"place":null,"contributors":null,"retweeted_status":{"metadata":{"iso_language_code":"en","result_type":"recent"},"created_at":"Fri Jun 12 20:26:45 +0000 2015","id":609456829173735425,"id_str":"609456829173735425","text":"Did Rap music do this to you? Did Emiinem, Justin Timberlake and Jusrtin Beiber do this to you.  #askrachel","source":"\u003ca href=\"http:\/\/twitter.com\" rel=\"nofollow\"\u003eTwitter Web Client\u003c\/a\u003e","truncated":false,"in_reply_to_status_id":null,"in_reply_to_status_id_str":null,"in_reply_to_user_id":null,"in_reply_to_user_id_str":null,"in_reply_to_screen_name":null,"user":{"id":35738808,"id_str":"35738808","name":"President Obonjo","screen_name":"Obonjo","location":"London ","description":"Stand up Comedian, President of Lafta Republic , Leader of the unfree world.","url":null,"entities":{"description":{"urls":[]}},"protected":false,"followers_count":1099,"friends_count":2001,"listed_count":15,"created_at":"Mon Apr 27 13:20:19 +0000 2009","favourites_count":117,"utc_offset":36000,"time_zone":"Brisbane","geo_enabled":false,"verified":false,"statuses_count":7228,"lang":"en","contributors_enabled":false,"is_translator":false,"is_translation_enabled":false,"profile_background_color":"BADFCD","profile_background_image_url":"http:\/\/pbs.twimg.com\/profile_background_images\/399228147\/Gospel1.jpg","profile_background_image_url_https":"https:\/\/pbs.twimg.com\/profile_background_images\/399228147\/Gospel1.jpg","profile_background_tile":false,"profile_image_url":"http:\/\/pbs.twimg.com\/profile_images\/553895401112104961\/-qqboRyD_normal.jpeg","profile_image_url_https":"https:\/\/pbs.twimg.com\/profile_images\/553895401112104961\/-qqboRyD_normal.jpeg","profile_banner_url":"https:\/\/pbs.twimg.com\/profile_banners\/35738808\/1420893977","profile_link_color":"FF0000","profile_sidebar_border_color":"F2E195","profile_sidebar_fill_color":"FFF7CC","profile_text_color":"0C3E53","profile_use_background_image":true,"default_profile":false,"default_profile_image":false,"following":null,"follow_request_sent":null,"notifications":null},"geo":null,"coordinates":null,"place":null,"contributors":null,"is_quote_status":false,"retweet_count":1,"favorite_count":1,"entities":{"hashtags":[{"text":"askrachel","indices":[97,107]}],"symbols":[],"user_mentions":[],"urls":[]},"favorited":false,"retweeted":false,"lang":"en"},"is_quote_status":false,"retweet_count":1,"favorite_count":0,"entities":{"hashtags":[{"text":"askrachel","indices":[109,119]}],"symbols":[],"user_mentions":[{"screen_name":"Obonjo","name":"President Obonjo","id":35738808,"id_str":"35738808","indices":[3,10]}],"urls":[]},"favorited":false,"retweeted":false,"lang":"en"},{"metadata":{"iso_language_code":"en","result_type":"recent"},"created_at":"Fri Jun 12 20:31:01 +0000 2015","id":609457902592622592,"id_str":"609457902592622592","text":"RT @tommymcnaughty: Last night after @TheComedyLoft we met Justin Beiber he was super nice. Never know what will happen in Hollywood. http:\u2026","source":"\u003ca href=\"http:\/\/twitter.com\/download\/android\" rel=\"nofollow\"\u003eTwitter for Android\u003c\/a\u003e","truncated":false,"in_reply_to_status_id":null,"in_reply_to_status_id_str":null,"in_reply_to_user_id":null,"in_reply_to_user_id_str":null,"in_reply_to_screen_name":null,"user":{"id":1131543282,"id_str":"1131543282","name":"    mica ","screen_name":"MICH4ELP00P","location":"arg","description":"BOLUDA ME SIGUE JUSTIN                                              i ship bullshit                                                                   #P4MEL4CHU","url":null,"entities":{"description":{"urls":[]}},"protected":false,"followers_count":4114,"friends_count":3745,"listed_count":4,"created_at":"Tue Jan 29 16:49:08 +0000 2013","favourites_count":3469,"utc_offset":-10800,"time_zone":"Buenos Aires","geo_enabled":false,"verified":false,"statuses_count":81420,"lang":"es","contributors_enabled":false,"is_translator":false,"is_translation_enabled":false,"profile_background_color":"FFFFFF","profile_background_image_url":"http:\/\/pbs.twimg.com\/profile_background_images\/453318369626697729\/cmizzfFo.jpeg","profile_background_image_url_https":"https:\/\/pbs.twimg.com\/profile_background_images\/453318369626697729\/cmizzfFo.jpeg","profile_background_tile":false,"profile_image_url":"http:\/\/pbs.twimg.com\/profile_images\/607742558693900288\/uPJkZg5r_normal.jpg","profile_image_url_https":"https:\/\/pbs.twimg.com\/profile_images\/607742558693900288\/uPJkZg5r_normal.jpg","profile_banner_url":"https:\/\/pbs.twimg.com\/profile_banners\/1131543282\/1431707846","profile_link_color":"DD2E44","profile_sidebar_border_color":"FFFFFF","profile_sidebar_fill_color":"F6F6F6","profile_text_color":"333333","profile_use_background_image":true,"default_profile":false,"default_profile_image":false,"following":null,"follow_request_sent":null,"notifications":null},"geo":null,"coordinates":null,"place":null,"contributors":null,"retweeted_status":{"metadata":{"iso_language_code":"en","result_type":"recent"},"created_at":"Tue Jun 09 21:32:48 +0000 2015","id":608386284604817409,"id_str":"608386284604817409","text":"Last night after @TheComedyLoft we met Justin Beiber he was super nice. Never know what will happen in Hollywood. http:\/\/t.co\/v0AuB33rDn","source":"\u003ca href=\"http:\/\/twitter.com\/download\/android\" rel=\"nofollow\"\u003eTwitter for Android\u003c\/a\u003e","truncated":false,"in_reply_to_status_id":null,"in_reply_to_status_id_str":null,"in_reply_to_user_id":null,"in_reply_to_user_id_str":null,"in_reply_to_screen_name":null,"user":{"id":2213396456,"id_str":"2213396456","name":"Tom McNaughton","screen_name":"tommymcnaughty","location":"","description":"Comedian and dog picker upper. coffee for blood. Internet confuses me.  http:\/\/t.co\/zvlz0xWYtl  St. Paul MN\/Los Angeles CA","url":null,"entities":{"description":{"urls":[{"url":"http:\/\/t.co\/zvlz0xWYtl","expanded_url":"http:\/\/favstar.fm\/users\/tommymcnaughty","display_url":"favstar.fm\/users\/tommymcn\u2026","indices":[72,94]}]}},"protected":false,"followers_count":1002,"friends_count":1305,"listed_count":9,"created_at":"Mon Nov 25 02:36:48 +0000 2013","favourites_count":2012,"utc_offset":null,"time_zone":null,"geo_enabled":false,"verified":false,"statuses_count":1042,"lang":"en","contributors_enabled":false,"is_translator":false,"is_translation_enabled":false,"profile_background_color":"000000","profile_background_image_url":"http:\/\/abs.twimg.com\/images\/themes\/theme1\/bg.png","profile_background_image_url_https":"https:\/\/abs.twimg.com\/images\/themes\/theme1\/bg.png","profile_background_tile":false,"profile_image_url":"http:\/\/pbs.twimg.com\/profile_images\/599622909653430273\/ycqNxPFG_normal.jpg","profile_image_url_https":"https:\/\/pbs.twimg.com\/profile_images\/599622909653430273\/ycqNxPFG_normal.jpg","profile_banner_url":"https:\/\/pbs.twimg.com\/profile_banners\/2213396456\/1410665197","profile_link_color":"4A913C","profile_sidebar_border_color":"000000","profile_sidebar_fill_color":"000000","profile_text_color":"000000","profile_use_background_image":false,"default_profile":false,"default_profile_image":false,"following":null,"follow_request_sent":null,"notifications":null},"geo":null,"coordinates":null,"place":null,"contributors":null,"is_quote_status":false,"retweet_count":1587,"favorite_count":1460,"entities":{"hashtags":[],"symbols":[],"user_mentions":[{"screen_name":"TheComedyLoft","name":"The Comedy Loft ","id":3240230154,"id_str":"3240230154","indices":[17,31]}],"urls":[],"media":[{"id":608386276887298048,"id_str":"608386276887298048","indices":[114,136],"media_url":"http:\/\/pbs.twimg.com\/media\/CHFsGHAXAAAhKbl.jpg","media_url_https":"https:\/\/pbs.twimg.com\/media\/CHFsGHAXAAAhKbl.jpg","url":"http:\/\/t.co\/v0AuB33rDn","display_url":"pic.twitter.com\/v0AuB33rDn","expanded_url":"http:\/\/twitter.com\/tommymcnaughty\/status\/608386284604817409\/photo\/1","type":"photo","sizes":{"small":{"w":340,"h":453,"resize":"fit"},"medium":{"w":600,"h":800,"resize":"fit"},"thumb":{"w":150,"h":150,"resize":"crop"},"large":{"w":768,"h":1024,"resize":"fit"}}}]},"favorited":false,"retweeted":false,"possibly_sensitive":false,"lang":"en"},"is_quote_status":false,"retweet_count":1587,"favorite_count":0,"entities":{"hashtags":[],"symbols":[],"user_mentions":[{"screen_name":"tommymcnaughty","name":"Tom McNaughton","id":2213396456,"id_str":"2213396456","indices":[3,18]},{"screen_name":"TheComedyLoft","name":"The Comedy Loft ","id":3240230154,"id_str":"3240230154","indices":[37,51]}],"urls":[],"media":[{"id":608386276887298048,"id_str":"608386276887298048","indices":[139,140],"media_url":"http:\/\/pbs.twimg.com\/media\/CHFsGHAXAAAhKbl.jpg","media_url_https":"https:\/\/pbs.twimg.com\/media\/CHFsGHAXAAAhKbl.jpg","url":"http:\/\/t.co\/v0AuB33rDn","display_url":"pic.twitter.com\/v0AuB33rDn","expanded_url":"http:\/\/twitter.com\/tommymcnaughty\/status\/608386284604817409\/photo\/1","type":"photo","sizes":{"small":{"w":340,"h":453,"resize":"fit"},"medium":{"w":600,"h":800,"resize":"fit"},"thumb":{"w":150,"h":150,"resize":"crop"},"large":{"w":768,"h":1024,"resize":"fit"}},"source_status_id":608386284604817409,"source_status_id_str":"608386284604817409","source_user_id":2213396456,"source_user_id_str":"2213396456"}]},"favorited":false,"retweeted":false,"possibly_sensitive":false,"lang":"en"},{"metadata":{"iso_language_code":"en","result_type":"recent"},"created_at":"Fri Jun 12 20:30:35 +0000 2015","id":609457791313518593,"id_str":"609457791313518593","text":"RT @CarlyLenz: when someone writes \"Justin Beiber is a shity singer\" on ur yearbook but spells bieber and shitty wrong","source":"\u003ca href=\"http:\/\/twitter.com\/download\/iphone\" rel=\"nofollow\"\u003eTwitter for iPhone\u003c\/a\u003e","truncated":false,"in_reply_to_status_id":null,"in_reply_to_status_id_str":null,"in_reply_to_user_id":null,"in_reply_to_user_id_str":null,"in_reply_to_screen_name":null,"user":{"id":1724267107,"id_str":"1724267107","name":"Daisy Dakota","screen_name":"KyraD29","location":"","description":"who will protect the people when the police break the law\u00bf?","url":null,"entities":{"description":{"urls":[]}},"protected":false,"followers_count":231,"friends_count":339,"listed_count":1,"created_at":"Tue Sep 03 03:24:44 +0000 2013","favourites_count":345,"utc_offset":null,"time_zone":null,"geo_enabled":false,"verified":false,"statuses_count":2166,"lang":"en","contributors_enabled":false,"is_translator":false,"is_translation_enabled":false,"profile_background_color":"C0DEED","profile_background_image_url":"http:\/\/abs.twimg.com\/images\/themes\/theme1\/bg.png","profile_background_image_url_https":"https:\/\/abs.twimg.com\/images\/themes\/theme1\/bg.png","profile_background_tile":false,"profile_image_url":"http:\/\/pbs.twimg.com\/profile_images\/600984043879038976\/722QIrjb_normal.jpg","profile_image_url_https":"https:\/\/pbs.twimg.com\/profile_images\/600984043879038976\/722QIrjb_normal.jpg","profile_banner_url":"https:\/\/pbs.twimg.com\/profile_banners\/1724267107\/1432787580","profile_link_color":"0084B4","profile_sidebar_border_color":"C0DEED","profile_sidebar_fill_color":"DDEEF6","profile_text_color":"333333","profile_use_background_image":true,"default_profile":true,"default_profile_image":false,"following":null,"follow_request_sent":null,"notifications":null},"geo":null,"coordinates":null,"place":null,"contributors":null,"retweeted_status":{"metadata":{"iso_language_code":"en","result_type":"recent"},"created_at":"Fri Jun 12 19:34:59 +0000 2015","id":609443799329296384,"id_str":"609443799329296384","text":"when someone writes \"Justin Beiber is a shity singer\" on ur yearbook but spells bieber and shitty wrong","source":"\u003ca href=\"http:\/\/twitter.com\/download\/iphone\" rel=\"nofollow\"\u003eTwitter for iPhone\u003c\/a\u003e","truncated":false,"in_reply_to_status_id":null,"in_reply_to_status_id_str":null,"in_reply_to_user_id":null,"in_reply_to_user_id_str":null,"in_reply_to_screen_name":null,"user":{"id":2188128549,"id_str":"2188128549","name":"Carly Lenz","screen_name":"CarlyLenz","location":"","description":"Bieber\u2655\u2661\u2671","url":null,"entities":{"description":{"urls":[]}},"protected":false,"followers_count":270,"friends_count":318,"listed_count":0,"created_at":"Wed Nov 20 00:13:40 +0000 2013","favourites_count":1000,"utc_offset":null,"time_zone":null,"geo_enabled":false,"verified":false,"statuses_count":2043,"lang":"en","contributors_enabled":false,"is_translator":false,"is_translation_enabled":false,"profile_background_color":"C0DEED","profile_background_image_url":"http:\/\/abs.twimg.com\/images\/themes\/theme1\/bg.png","profile_background_image_url_https":"https:\/\/abs.twimg.com\/images\/themes\/theme1\/bg.png","profile_background_tile":false,"profile_image_url":"http:\/\/pbs.twimg.com\/profile_images\/605878501258829824\/ubzVa_fC_normal.jpg","profile_image_url_https":"https:\/\/pbs.twimg.com\/profile_images\/605878501258829824\/ubzVa_fC_normal.jpg","profile_banner_url":"https:\/\/pbs.twimg.com\/profile_banners\/2188128549\/1433360173","profile_link_color":"0084B4","profile_sidebar_border_color":"C0DEED","profile_sidebar_fill_color":"DDEEF6","profile_text_color":"333333","profile_use_background_image":true,"default_profile":true,"default_profile_image":false,"following":null,"follow_request_sent":null,"notifications":null},"geo":null,"coordinates":null,"place":null,"contributors":null,"is_quote_status":false,"retweet_count":1,"favorite_count":6,"entities":{"hashtags":[],"symbols":[],"user_mentions":[],"urls":[]},"favorited":false,"retweeted":false,"lang":"en"},"is_quote_status":false,"retweet_count":1,"favorite_count":0,"entities":{"hashtags":[],"symbols":[],"user_mentions":[{"screen_name":"CarlyLenz","name":"Carly Lenz","id":2188128549,"id_str":"2188128549","indices":[3,13]}],"urls":[]},"favorited":false,"retweeted":false,"lang":"en"},{"metadata":{"iso_language_code":"en","result_type":"recent"},"created_at":"Fri Jun 12 20:29:11 +0000 2015","id":609457439038160896,"id_str":"609457439038160896","text":"Justin beiber eminem and iggy Azalia all adopt black culture with having white privilege","source":"\u003ca href=\"http:\/\/twitter.com\/download\/android\" rel=\"nofollow\"\u003eTwitter for Android\u003c\/a\u003e","truncated":false,"in_reply_to_status_id":null,"in_reply_to_status_id_str":null,"in_reply_to_user_id":null,"in_reply_to_user_id_str":null,"in_reply_to_screen_name":null,"user":{"id":98803318,"id_str":"98803318","name":"U LOVE MY FRECKLES","screen_name":"WhatUSayBxtch","location":"IN MY BED","description":"Ask Me No Questions And I'll Tell You No Lies","url":null,"entities":{"description":{"urls":[]}},"protected":false,"followers_count":294,"friends_count":179,"listed_count":6,"created_at":"Wed Dec 23 05:15:28 +0000 2009","favourites_count":73,"utc_offset":-14400,"time_zone":"Eastern Time (US & Canada)","geo_enabled":true,"verified":false,"statuses_count":25065,"lang":"en","contributors_enabled":false,"is_translator":false,"is_translation_enabled":false,"profile_background_color":"D6514F","profile_background_image_url":"http:\/\/pbs.twimg.com\/profile_background_images\/323446554\/Nicki-Minaj-Glamour-Magazine-5.png","profile_background_image_url_https":"https:\/\/pbs.twimg.com\/profile_background_images\/323446554\/Nicki-Minaj-Glamour-Magazine-5.png","profile_background_tile":false,"profile_image_url":"http:\/\/pbs.twimg.com\/profile_images\/578732745150562304\/UVtv5qTI_normal.jpeg","profile_image_url_https":"https:\/\/pbs.twimg.com\/profile_images\/578732745150562304\/UVtv5qTI_normal.jpeg","profile_link_color":"D41196","profile_sidebar_border_color":"030303","profile_sidebar_fill_color":"050505","profile_text_color":"40DED6","profile_use_background_image":true,"default_profile":false,"default_profile_image":false,"following":null,"follow_request_sent":null,"notifications":null},"geo":null,"coordinates":null,"place":null,"contributors":null,"is_quote_status":false,"retweet_count":0,"favorite_count":0,"entities":{"hashtags":[],"symbols":[],"user_mentions":[],"urls":[]},"favorited":false,"retweeted":false,"lang":"en"},{"metadata":{"iso_language_code":"en","result_type":"recent"},"created_at":"Fri Jun 12 20:26:45 +0000 2015","id":609456829173735425,"id_str":"609456829173735425","text":"Did Rap music do this to you? Did Emiinem, Justin Timberlake and Jusrtin Beiber do this to you.  #askrachel","source":"\u003ca href=\"http:\/\/twitter.com\" rel=\"nofollow\"\u003eTwitter Web Client\u003c\/a\u003e","truncated":false,"in_reply_to_status_id":null,"in_reply_to_status_id_str":null,"in_reply_to_user_id":null,"in_reply_to_user_id_str":null,"in_reply_to_screen_name":null,"user":{"id":35738808,"id_str":"35738808","name":"President Obonjo","screen_name":"Obonjo","location":"London ","description":"Stand up Comedian, President of Lafta Republic , Leader of the unfree world.","url":null,"entities":{"description":{"urls":[]}},"protected":false,"followers_count":1099,"friends_count":2001,"listed_count":15,"created_at":"Mon Apr 27 13:20:19 +0000 2009","favourites_count":117,"utc_offset":36000,"time_zone":"Brisbane","geo_enabled":false,"verified":false,"statuses_count":7228,"lang":"en","contributors_enabled":false,"is_translator":false,"is_translation_enabled":false,"profile_background_color":"BADFCD","profile_background_image_url":"http:\/\/pbs.twimg.com\/profile_background_images\/399228147\/Gospel1.jpg","profile_background_image_url_https":"https:\/\/pbs.twimg.com\/profile_background_images\/399228147\/Gospel1.jpg","profile_background_tile":false,"profile_image_url":"http:\/\/pbs.twimg.com\/profile_images\/553895401112104961\/-qqboRyD_normal.jpeg","profile_image_url_https":"https:\/\/pbs.twimg.com\/profile_images\/553895401112104961\/-qqboRyD_normal.jpeg","profile_banner_url":"https:\/\/pbs.twimg.com\/profile_banners\/35738808\/1420893977","profile_link_color":"FF0000","profile_sidebar_border_color":"F2E195","profile_sidebar_fill_color":"FFF7CC","profile_text_color":"0C3E53","profile_use_background_image":true,"default_profile":false,"default_profile_image":false,"following":null,"follow_request_sent":null,"notifications":null},"geo":null,"coordinates":null,"place":null,"contributors":null,"is_quote_status":false,"retweet_count":1,"favorite_count":1,"entities":{"hashtags":[{"text":"askrachel","indices":[97,107]}],"symbols":[],"user_mentions":[],"urls":[]},"favorited":false,"retweeted":false,"lang":"en"},{"metadata":{"iso_language_code":"en","result_type":"recent"},"created_at":"Fri Jun 12 20:25:51 +0000 2015","id":609456600026357760,"id_str":"609456600026357760","text":"RT @tylergposey: I woke up with a Justin beiber song and a one direction song stuck in my head. What's happening to me. I blame @dylanobrien","source":"\u003ca href=\"http:\/\/twitter.com\" rel=\"nofollow\"\u003eTwitter Web Client\u003c\/a\u003e","truncated":false,"in_reply_to_status_id":null,"in_reply_to_status_id_str":null,"in_reply_to_user_id":null,"in_reply_to_user_id_str":null,"in_reply_to_screen_name":null,"user":{"id":42007261,"id_str":"42007261","name":"Merr Puckle.","screen_name":"Hermstern","location":"N\u03b5\u03ba\u03c1\u03cc\u03c0\u03bf\u03bb\u03b9\u03c2","description":"Cronarca, trujam\u00e1n, banshee.","url":"http:\/\/t.co\/Ckn5y6NYcK","entities":{"url":{"urls":[{"url":"http:\/\/t.co\/Ckn5y6NYcK","expanded_url":"http:\/\/talesofmidgard.tumblr.com","display_url":"talesofmidgard.tumblr.com","indices":[0,22]}]},"description":{"urls":[]}},"protected":false,"followers_count":282,"friends_count":131,"listed_count":21,"created_at":"Sat May 23 10:30:21 +0000 2009","favourites_count":4075,"utc_offset":7200,"time_zone":"Madrid","geo_enabled":true,"verified":false,"statuses_count":75739,"lang":"es","contributors_enabled":false,"is_translator":false,"is_translation_enabled":false,"profile_background_color":"FFFFFF","profile_background_image_url":"http:\/\/pbs.twimg.com\/profile_background_images\/803534047\/fb10a968a3cdbe9af1899554ed26570b.jpeg","profile_background_image_url_https":"https:\/\/pbs.twimg.com\/profile_background_images\/803534047\/fb10a968a3cdbe9af1899554ed26570b.jpeg","profile_background_tile":true,"profile_image_url":"http:\/\/pbs.twimg.com\/profile_images\/585572188792709122\/5nRElMDz_normal.jpg","profile_image_url_https":"https:\/\/pbs.twimg.com\/profile_images\/585572188792709122\/5nRElMDz_normal.jpg","profile_banner_url":"https:\/\/pbs.twimg.com\/profile_banners\/42007261\/1425419437","profile_link_color":"956A6A","profile_sidebar_border_color":"FFFFFF","profile_sidebar_fill_color":"0F0F0F","profile_text_color":"636263","profile_use_background_image":true,"default_profile":false,"default_profile_image":false,"following":null,"follow_request_sent":null,"notifications":null},"geo":null,"coordinates":null,"place":null,"contributors":null,"retweeted_status":{"metadata":{"iso_language_code":"en","result_type":"recent"},"created_at":"Tue Oct 23 18:28:07 +0000 2012","id":260809847740694528,"id_str":"260809847740694528","text":"I woke up with a Justin beiber song and a one direction song stuck in my head. What's happening to me. I blame @dylanobrien","source":"\u003ca href=\"http:\/\/twitter.com\/download\/iphone\" rel=\"nofollow\"\u003eTwitter for iPhone\u003c\/a\u003e","truncated":false,"in_reply_to_status_id":null,"in_reply_to_status_id_str":null,"in_reply_to_user_id":null,"in_reply_to_user_id_str":null,"in_reply_to_screen_name":null,"user":{"id":169740780,"id_str":"169740780","name":"tyler posey","screen_name":"tylergposey","location":"","description":"music for your ears to bleed to","url":"http:\/\/t.co\/csAqinEwiS","entities":{"url":{"urls":[{"url":"http:\/\/t.co\/csAqinEwiS","expanded_url":"http:\/\/youtube.com\/lostinkostko","display_url":"youtube.com\/lostinkostko","indices":[0,22]}]},"description":{"urls":[]}},"protected":false,"followers_count":1625037,"friends_count":1786,"listed_count":5453,"created_at":"Fri Jul 23 01:54:22 +0000 2010","favourites_count":178,"utc_offset":null,"time_zone":null,"geo_enabled":false,"verified":true,"statuses_count":11733,"lang":"en","contributors_enabled":false,"is_translator":false,"is_translation_enabled":true,"profile_background_color":"FEEFDA","profile_background_image_url":"http:\/\/pbs.twimg.com\/profile_background_images\/338602055\/25lti.jpg","profile_background_image_url_https":"https:\/\/pbs.twimg.com\/profile_background_images\/338602055\/25lti.jpg","profile_background_tile":true,"profile_image_url":"http:\/\/pbs.twimg.com\/profile_images\/552917904430092288\/x2DFnq_B_normal.jpeg","profile_image_url_https":"https:\/\/pbs.twimg.com\/profile_images\/552917904430092288\/x2DFnq_B_normal.jpeg","profile_banner_url":"https:\/\/pbs.twimg.com\/profile_banners\/169740780\/1424909209","profile_link_color":"000000","profile_sidebar_border_color":"B9491B","profile_sidebar_fill_color":"E7DAC7","profile_text_color":"000000","profile_use_background_image":true,"default_profile":false,"default_profile_image":false,"following":null,"follow_request_sent":null,"notifications":null},"geo":null,"coordinates":null,"place":null,"contributors":null,"is_quote_status":false,"retweet_count":5465,"favorite_count":5576,"entities":{"hashtags":[],"symbols":[],"user_mentions":[{"screen_name":"dylanobrien","name":"Dylan O'Brien","id":281766200,"id_str":"281766200","indices":[111,123]}],"urls":[]},"favorited":false,"retweeted":false,"lang":"en"},"is_quote_status":false,"retweet_count":5465,"favorite_count":0,"entities":{"hashtags":[],"symbols":[],"user_mentions":[{"screen_name":"tylergposey","name":"tyler posey","id":169740780,"id_str":"169740780","indices":[3,15]},{"screen_name":"dylanobrien","name":"Dylan O'Brien","id":281766200,"id_str":"281766200","indices":[128,140]}],"urls":[]},"favorited":false,"retweeted":false,"lang":"en"},{"metadata":{"iso_language_code":"en","result_type":"recent"},"created_at":"Fri Jun 12 20:24:10 +0000 2015","id":609456177727041537,"id_str":"609456177727041537","text":"RT @1Dloveme5SOS: \ud83d\udc9cRt for a solo DM with Justin Beiber \ud83d\udc9c\n\nMbf\n\nChoosing 4","source":"\u003ca href=\"http:\/\/twitter.com\/download\/android\" rel=\"nofollow\"\u003eTwitter for Android\u003c\/a\u003e","truncated":false,"in_reply_to_status_id":null,"in_reply_to_status_id_str":null,"in_reply_to_user_id":null,"in_reply_to_user_id_str":null,"in_reply_to_screen_name":null,"user":{"id":1370543293,"id_str":"1370543293","name":"Nair","screen_name":"horan_nair","location":"Paraguay","description":"\u2020No matter the time\u2020 \u2022One direction\u2022 || la sonrisa de louis como religion|| nadie me sigue pierdes el tiempo 0\/5(?\u2022","url":null,"entities":{"description":{"urls":[]}},"protected":false,"followers_count":1299,"friends_count":1999,"listed_count":3,"created_at":"Sun Apr 21 20:39:18 +0000 2013","favourites_count":2834,"utc_offset":-25200,"time_zone":"Arizona","geo_enabled":true,"verified":false,"statuses_count":7162,"lang":"es","contributors_enabled":false,"is_translator":false,"is_translation_enabled":false,"profile_background_color":"89C9FA","profile_background_image_url":"http:\/\/pbs.twimg.com\/profile_background_images\/378800000108334412\/68e571686af13e564f5f0045a8cce033.png","profile_background_image_url_https":"https:\/\/pbs.twimg.com\/profile_background_images\/378800000108334412\/68e571686af13e564f5f0045a8cce033.png","profile_background_tile":true,"profile_image_url":"http:\/\/pbs.twimg.com\/profile_images\/608128121175441408\/ElBzINfh_normal.jpg","profile_image_url_https":"https:\/\/pbs.twimg.com\/profile_images\/608128121175441408\/ElBzINfh_normal.jpg","profile_banner_url":"https:\/\/pbs.twimg.com\/profile_banners\/1370543293\/1433694192","profile_link_color":"3B94D9","profile_sidebar_border_color":"FFFFFF","profile_sidebar_fill_color":"DDEEF6","profile_text_color":"333333","profile_use_background_image":true,"default_profile":false,"default_profile_image":false,"following":null,"follow_request_sent":null,"notifications":null},"geo":null,"coordinates":null,"place":null,"contributors":null,"retweeted_status":{"metadata":{"iso_language_code":"en","result_type":"recent"},"created_at":"Fri Jun 12 19:55:38 +0000 2015","id":609448997497933825,"id_str":"609448997497933825","text":"\ud83d\udc9cRt for a solo DM with Justin Beiber \ud83d\udc9c\n\nMbf\n\nChoosing 4","source":"\u003ca href=\"http:\/\/twitter.com\/download\/android\" rel=\"nofollow\"\u003eTwitter for Android\u003c\/a\u003e","truncated":false,"in_reply_to_status_id":null,"in_reply_to_status_id_str":null,"in_reply_to_user_id":null,"in_reply_to_user_id_str":null,"in_reply_to_screen_name":null,"user":{"id":2788781052,"id_str":"2788781052","name":"\u2693Harry Is Sex\u2693\ufe0f","screen_name":"1Dloveme5SOS","location":"\u2600\ufe0fNotifs on for DMs\u2600\ufe0f","description":"\u2601Yeah we're looking down on the clouds\u2601\ufe0f BA\/4\u2693\ufe0f0\/5\u2693\ufe0f DM Access w\/: 5\/4 + 6\/5\u2693\ufe0f","url":"https:\/\/t.co\/nvc251fuzz","entities":{"url":{"urls":[{"url":"https:\/\/t.co\/nvc251fuzz","expanded_url":"https:\/\/docs.google.com\/forms\/d\/19S_8kJ8ihpNgbAHdwSAXkz8nr7L8137vIizJGxCH114\/viewform?usp=send_form","display_url":"docs.google.com\/forms\/d\/19S_8k\u2026","indices":[0,23]}]},"description":{"urls":[]}},"protected":false,"followers_count":6872,"friends_count":5313,"listed_count":10,"created_at":"Wed Sep 03 23:45:48 +0000 2014","favourites_count":4881,"utc_offset":null,"time_zone":null,"geo_enabled":true,"verified":false,"statuses_count":20701,"lang":"en","contributors_enabled":false,"is_translator":false,"is_translation_enabled":false,"profile_background_color":"000000","profile_background_image_url":"http:\/\/abs.twimg.com\/images\/themes\/theme1\/bg.png","profile_background_image_url_https":"https:\/\/abs.twimg.com\/images\/themes\/theme1\/bg.png","profile_background_tile":false,"profile_image_url":"http:\/\/pbs.twimg.com\/profile_images\/606531038370754560\/19NzA1qD_normal.jpg","profile_image_url_https":"https:\/\/pbs.twimg.com\/profile_images\/606531038370754560\/19NzA1qD_normal.jpg","profile_banner_url":"https:\/\/pbs.twimg.com\/profile_banners\/2788781052\/1433443242","profile_link_color":"9266CC","profile_sidebar_border_color":"000000","profile_sidebar_fill_color":"000000","profile_text_color":"000000","profile_use_background_image":false,"default_profile":false,"default_profile_image":false,"following":null,"follow_request_sent":null,"notifications":null},"geo":null,"coordinates":null,"place":null,"contributors":null,"is_quote_status":false,"retweet_count":6,"favorite_count":1,"entities":{"hashtags":[],"symbols":[],"user_mentions":[],"urls":[]},"favorited":false,"retweeted":false,"lang":"en"},"is_quote_status":false,"retweet_count":6,"favorite_count":0,"entities":{"hashtags":[],"symbols":[],"user_mentions":[{"screen_name":"1Dloveme5SOS","name":"\u2693Harry Is Sex\u2693\ufe0f","id":2788781052,"id_str":"2788781052","indices":[3,16]}],"urls":[]},"favorited":false,"retweeted":false,"lang":"en"},{"metadata":{"iso_language_code":"en","result_type":"recent"},"created_at":"Fri Jun 12 20:19:31 +0000 2015","id":609455007910469633,"id_str":"609455007910469633","text":"Justin Beiber surprise performances at Hong Kong Calvin Klein Underwear Show.","source":"\u003ca href=\"http:\/\/twitter.com\" rel=\"nofollow\"\u003eTwitter Web Client\u003c\/a\u003e","truncated":false,"in_reply_to_status_id":null,"in_reply_to_status_id_str":null,"in_reply_to_user_id":null,"in_reply_to_user_id_str":null,"in_reply_to_screen_name":null,"user":{"id":3217107095,"id_str":"3217107095","name":"Ramone Oscar","screen_name":"ramoneoscar2","location":"","description":"","url":null,"entities":{"description":{"urls":[]}},"protected":false,"followers_count":4,"friends_count":56,"listed_count":1,"created_at":"Tue Apr 28 13:08:28 +0000 2015","favourites_count":12,"utc_offset":null,"time_zone":null,"geo_enabled":false,"verified":false,"statuses_count":125,"lang":"en","contributors_enabled":false,"is_translator":false,"is_translation_enabled":false,"profile_background_color":"C0DEED","profile_background_image_url":"http:\/\/abs.twimg.com\/images\/themes\/theme1\/bg.png","profile_background_image_url_https":"https:\/\/abs.twimg.com\/images\/themes\/theme1\/bg.png","profile_background_tile":false,"profile_image_url":"http:\/\/abs.twimg.com\/sticky\/default_profile_images\/default_profile_6_normal.png","profile_image_url_https":"https:\/\/abs.twimg.com\/sticky\/default_profile_images\/default_profile_6_normal.png","profile_link_color":"0084B4","profile_sidebar_border_color":"C0DEED","profile_sidebar_fill_color":"DDEEF6","profile_text_color":"333333","profile_use_background_image":true,"default_profile":true,"default_profile_image":true,"following":null,"follow_request_sent":null,"notifications":null},"geo":null,"coordinates":null,"place":null,"contributors":null,"is_quote_status":false,"retweet_count":0,"favorite_count":0,"entities":{"hashtags":[],"symbols":[],"user_mentions":[],"urls":[]},"favorited":false,"retweeted":false,"lang":"en"},{"metadata":{"iso_language_code":"en","result_type":"recent"},"created_at":"Fri Jun 12 20:19:24 +0000 2015","id":609454976876851201,"id_str":"609454976876851201","text":"@justinbieber Yo Justin Beiber Come back to Toronto I want to make a track with you","source":"\u003ca href=\"http:\/\/twitter.com\/download\/android\" rel=\"nofollow\"\u003eTwitter for Android\u003c\/a\u003e","truncated":false,"in_reply_to_status_id":null,"in_reply_to_status_id_str":null,"in_reply_to_user_id":27260086,"in_reply_to_user_id_str":"27260086","in_reply_to_screen_name":"justinbieber","user":{"id":333761877,"id_str":"333761877","name":"E Xavier ","screen_name":"XavierLoneWolf","location":"  Ontario Canada","description":"20  Ghanian        AMEN, Find your positive vibes G","url":null,"entities":{"description":{"urls":[]}},"protected":false,"followers_count":170,"friends_count":208,"listed_count":0,"created_at":"Tue Jul 12 01:47:05 +0000 2011","favourites_count":66,"utc_offset":-18000,"time_zone":"Quito","geo_enabled":false,"verified":false,"statuses_count":1649,"lang":"en","contributors_enabled":false,"is_translator":false,"is_translation_enabled":false,"profile_background_color":"000000","profile_background_image_url":"http:\/\/abs.twimg.com\/images\/themes\/theme15\/bg.png","profile_background_image_url_https":"https:\/\/abs.twimg.com\/images\/themes\/theme15\/bg.png","profile_background_tile":false,"profile_image_url":"http:\/\/pbs.twimg.com\/profile_images\/609185923587162112\/y7ynt2uL_normal.jpg","profile_image_url_https":"https:\/\/pbs.twimg.com\/profile_images\/609185923587162112\/y7ynt2uL_normal.jpg","profile_banner_url":"https:\/\/pbs.twimg.com\/profile_banners\/333761877\/1434071938","profile_link_color":"ABB8C2","profile_sidebar_border_color":"000000","profile_sidebar_fill_color":"000000","profile_text_color":"000000","profile_use_background_image":false,"default_profile":false,"default_profile_image":false,"following":null,"follow_request_sent":null,"notifications":null},"geo":null,"coordinates":null,"place":null,"contributors":null,"is_quote_status":false,"retweet_count":0,"favorite_count":0,"entities":{"hashtags":[],"symbols":[],"user_mentions":[{"screen_name":"justinbieber","name":"Justin Bieber","id":27260086,"id_str":"27260086","indices":[0,13]}],"urls":[]},"favorited":false,"retweeted":false,"lang":"en"},{"metadata":{"iso_language_code":"en","result_type":"recent"},"created_at":"Fri Jun 12 20:18:44 +0000 2015","id":609454809306005506,"id_str":"609454809306005506","text":"RT @jaefromvine: Justin Beiber - Hold on tight \ud83d\ude0c","source":"\u003ca href=\"http:\/\/twitter.com\/download\/iphone\" rel=\"nofollow\"\u003eTwitter for iPhone\u003c\/a\u003e","truncated":false,"in_reply_to_status_id":null,"in_reply_to_status_id_str":null,"in_reply_to_user_id":null,"in_reply_to_user_id_str":null,"in_reply_to_screen_name":null,"user":{"id":383489454,"id_str":"383489454","name":"\u2728","screen_name":"Lady_CakinIt","location":"","description":"reality is overrated","url":null,"entities":{"description":{"urls":[]}},"protected":false,"followers_count":2227,"friends_count":2004,"listed_count":3,"created_at":"Sun Oct 02 00:03:26 +0000 2011","favourites_count":3330,"utc_offset":-10800,"time_zone":"Atlantic Time (Canada)","geo_enabled":true,"verified":false,"statuses_count":14616,"lang":"en","contributors_enabled":false,"is_translator":false,"is_translation_enabled":false,"profile_background_color":"709397","profile_background_image_url":"http:\/\/abs.twimg.com\/images\/themes\/theme6\/bg.gif","profile_background_image_url_https":"https:\/\/abs.twimg.com\/images\/themes\/theme6\/bg.gif","profile_background_tile":false,"profile_image_url":"http:\/\/pbs.twimg.com\/profile_images\/609287788861751296\/r9zRycem_normal.jpg","profile_image_url_https":"https:\/\/pbs.twimg.com\/profile_images\/609287788861751296\/r9zRycem_normal.jpg","profile_banner_url":"https:\/\/pbs.twimg.com\/profile_banners\/383489454\/1426391779","profile_link_color":"FF3300","profile_sidebar_border_color":"86A4A6","profile_sidebar_fill_color":"A0C5C7","profile_text_color":"333333","profile_use_background_image":true,"default_profile":false,"default_profile_image":false,"following":null,"follow_request_sent":null,"notifications":null},"geo":null,"coordinates":null,"place":null,"contributors":null,"retweeted_status":{"metadata":{"iso_language_code":"en","result_type":"recent"},"created_at":"Thu Jun 11 02:48:02 +0000 2015","id":608828004173795328,"id_str":"608828004173795328","text":"Justin Beiber - Hold on tight \ud83d\ude0c","source":"\u003ca href=\"http:\/\/twitter.com\/download\/iphone\" rel=\"nofollow\"\u003eTwitter for iPhone\u003c\/a\u003e","truncated":false,"in_reply_to_status_id":null,"in_reply_to_status_id_str":null,"in_reply_to_user_id":null,"in_reply_to_user_id_str":null,"in_reply_to_screen_name":null,"user":{"id":238491689,"id_str":"238491689","name":"JAIMESHA.","screen_name":"jaefromvine","location":"DC | IG: jaefromvine","description":"Leek\u2764\ufe0f","url":"http:\/\/t.co\/th65CQ9oeJ","entities":{"url":{"urls":[{"url":"http:\/\/t.co\/th65CQ9oeJ","expanded_url":"http:\/\/daretohavehair.com","display_url":"daretohavehair.com","indices":[0,22]}]},"description":{"urls":[]}},"protected":false,"followers_count":118499,"friends_count":2950,"listed_count":95,"created_at":"Sat Jan 15 08:48:50 +0000 2011","favourites_count":102,"utc_offset":-18000,"time_zone":"Central Time (US & Canada)","geo_enabled":false,"verified":false,"statuses_count":30513,"lang":"en","contributors_enabled":false,"is_translator":false,"is_translation_enabled":false,"profile_background_color":"9AE4E8","profile_background_image_url":"http:\/\/pbs.twimg.com\/profile_background_images\/545484838\/E.T.jpg","profile_background_image_url_https":"https:\/\/pbs.twimg.com\/profile_background_images\/545484838\/E.T.jpg","profile_background_tile":false,"profile_image_url":"http:\/\/pbs.twimg.com\/profile_images\/592528551557103616\/ByN-jGfh_normal.jpg","profile_image_url_https":"https:\/\/pbs.twimg.com\/profile_images\/592528551557103616\/ByN-jGfh_normal.jpg","profile_banner_url":"https:\/\/pbs.twimg.com\/profile_banners\/238491689\/1432001656","profile_link_color":"0084B4","profile_sidebar_border_color":"BDDCAD","profile_sidebar_fill_color":"DDFFCC","profile_text_color":"333333","profile_use_background_image":true,"default_profile":false,"default_profile_image":false,"following":null,"follow_request_sent":null,"notifications":null},"geo":null,"coordinates":null,"place":null,"contributors":null,"is_quote_status":false,"retweet_count":199,"favorite_count":196,"entities":{"hashtags":[],"symbols":[],"user_mentions":[],"urls":[]},"favorited":false,"retweeted":false,"lang":"en"},"is_quote_status":false,"retweet_count":199,"favorite_count":0,"entities":{"hashtags":[],"symbols":[],"user_mentions":[{"screen_name":"jaefromvine","name":"JAIMESHA.","id":238491689,"id_str":"238491689","indices":[3,15]}],"urls":[]},"favorited":false,"retweeted":false,"lang":"en"},{"metadata":{"iso_language_code":"en","result_type":"recent"},"created_at":"Fri Jun 12 20:16:48 +0000 2015","id":609454323911802880,"id_str":"609454323911802880","text":"RT @rosalind_eshika: TBH I'M SO PROUD KAI FOLLOWED SLIPKNOT, LINKIN PARK ETC\nALWAYS RMBR RUKI FOLLOWS JUSTIN BEIBER","source":"\u003ca href=\"http:\/\/www.twitter.com\" rel=\"nofollow\"\u003eTwitter for Windows Phone\u003c\/a\u003e","truncated":false,"in_reply_to_status_id":null,"in_reply_to_status_id_str":null,"in_reply_to_user_id":null,"in_reply_to_user_id_str":null,"in_reply_to_screen_name":null,"user":{"id":312141727,"id_str":"312141727","name":"|K|yussan","screen_name":"rukeita_hero","location":"Italy, Puglia, Bari","description":"\u3010Ambitious \u30ed Square\u3011DIRTY BEAST INSIDE | Uruha-san wa sugoi \u2665 R.U.K.E.I.T.A \u2665 R&R  FOLLOW THIS SHITxxx!!! 1996.10.5","url":"http:\/\/t.co\/rQRX9TSURd","entities":{"url":{"urls":[{"url":"http:\/\/t.co\/rQRX9TSURd","expanded_url":"http:\/\/flavors.me\/kata_no_etcetera","display_url":"flavors.me\/kata_no_etcete\u2026","indices":[0,22]}]},"description":{"urls":[]}},"protected":false,"followers_count":34,"friends_count":32,"listed_count":0,"created_at":"Mon Jun 06 17:04:40 +0000 2011","favourites_count":2788,"utc_offset":10800,"time_zone":"Athens","geo_enabled":true,"verified":false,"statuses_count":8767,"lang":"it","contributors_enabled":false,"is_translator":false,"is_translation_enabled":false,"profile_background_color":"000000","profile_background_image_url":"http:\/\/pbs.twimg.com\/profile_background_images\/718534268\/4df091d9bec6c944663d84d070ec97b7.jpeg","profile_background_image_url_https":"https:\/\/pbs.twimg.com\/profile_background_images\/718534268\/4df091d9bec6c944663d84d070ec97b7.jpeg","profile_background_tile":false,"profile_image_url":"http:\/\/pbs.twimg.com\/profile_images\/608038130638307329\/8h-lEQ-3_normal.jpg","profile_image_url_https":"https:\/\/pbs.twimg.com\/profile_images\/608038130638307329\/8h-lEQ-3_normal.jpg","profile_banner_url":"https:\/\/pbs.twimg.com\/profile_banners\/312141727\/1353601373","profile_link_color":"007BFF","profile_sidebar_border_color":"000000","profile_sidebar_fill_color":"DDEEF6","profile_text_color":"333333","profile_use_background_image":true,"default_profile":false,"default_profile_image":false,"following":null,"follow_request_sent":null,"notifications":null},"geo":null,"coordinates":null,"place":null,"contributors":null,"retweeted_status":{"metadata":{"iso_language_code":"en","result_type":"recent"},"created_at":"Thu Jun 11 13:10:09 +0000 2015","id":608984565567193088,"id_str":"608984565567193088","text":"TBH I'M SO PROUD KAI FOLLOWED SLIPKNOT, LINKIN PARK ETC\nALWAYS RMBR RUKI FOLLOWS JUSTIN BEIBER","source":"\u003ca href=\"https:\/\/mobile.twitter.com\" rel=\"nofollow\"\u003eMobile Web (M2)\u003c\/a\u003e","truncated":false,"in_reply_to_status_id":null,"in_reply_to_status_id_str":null,"in_reply_to_user_id":null,"in_reply_to_user_id_str":null,"in_reply_to_screen_name":null,"user":{"id":2288151926,"id_str":"2288151926","name":"yvtaka.","screen_name":"rosalind_eshika","location":"wherever Kai shackles me to","description":"19 | Guitarist | Sixth Gun | \u2661 KAI \u2661 | #ReitukiSquad| Part-time Physicist\/Full-time Weeb | The GazettE's drummer owns my heart~\r\nInstagram: @abandon_instinct","url":"http:\/\/t.co\/sXoBLUnQuO","entities":{"url":{"urls":[{"url":"http:\/\/t.co\/sXoBLUnQuO","expanded_url":"http:\/\/www.kuronekoojousama.tumblr.com","display_url":"kuronekoojousama.tumblr.com","indices":[0,22]}]},"description":{"urls":[]}},"protected":false,"followers_count":271,"friends_count":343,"listed_count":8,"created_at":"Sun Jan 12 13:08:11 +0000 2014","favourites_count":4698,"utc_offset":null,"time_zone":null,"geo_enabled":true,"verified":false,"statuses_count":13758,"lang":"en","contributors_enabled":false,"is_translator":false,"is_translation_enabled":false,"profile_background_color":"ACDED6","profile_background_image_url":"http:\/\/pbs.twimg.com\/profile_background_images\/453527595980554241\/RClBdU21.jpeg","profile_background_image_url_https":"https:\/\/pbs.twimg.com\/profile_background_images\/453527595980554241\/RClBdU21.jpeg","profile_background_tile":false,"profile_image_url":"http:\/\/pbs.twimg.com\/profile_images\/608475718029156352\/bIHICKFx_normal.jpg","profile_image_url_https":"https:\/\/pbs.twimg.com\/profile_images\/608475718029156352\/bIHICKFx_normal.jpg","profile_banner_url":"https:\/\/pbs.twimg.com\/profile_banners\/2288151926\/1433904840","profile_link_color":"3B14D9","profile_sidebar_border_color":"FFFFFF","profile_sidebar_fill_color":"DDEEF6","profile_text_color":"333333","profile_use_background_image":true,"default_profile":false,"default_profile_image":false,"following":null,"follow_request_sent":null,"notifications":null},"geo":null,"coordinates":null,"place":null,"contributors":null,"is_quote_status":false,"retweet_count":17,"favorite_count":13,"entities":{"hashtags":[],"symbols":[],"user_mentions":[],"urls":[]},"favorited":false,"retweeted":false,"lang":"en"},"is_quote_status":false,"retweet_count":17,"favorite_count":0,"entities":{"hashtags":[],"symbols":[],"user_mentions":[{"screen_name":"rosalind_eshika","name":"yvtaka.","id":2288151926,"id_str":"2288151926","indices":[3,19]}],"urls":[]},"favorited":false,"retweeted":false,"lang":"en"},{"metadata":{"iso_language_code":"en","result_type":"recent"},"created_at":"Fri Jun 12 20:14:52 +0000 2015","id":609453836483203072,"id_str":"609453836483203072","text":"Following justin beiber on snapchat was one of my best decisions evrrr \u263a\ufe0f\ud83d\ude18","source":"\u003ca href=\"http:\/\/twitter.com\/download\/iphone\" rel=\"nofollow\"\u003eTwitter for iPhone\u003c\/a\u003e","truncated":false,"in_reply_to_status_id":null,"in_reply_to_status_id_str":null,"in_reply_to_user_id":null,"in_reply_to_user_id_str":null,"in_reply_to_screen_name":null,"user":{"id":472598976,"id_str":"472598976","name":"karla","screen_name":"vananeG","location":" \u2708\ufe0f","description":"valley","url":null,"entities":{"description":{"urls":[]}},"protected":false,"followers_count":352,"friends_count":369,"listed_count":0,"created_at":"Tue Jan 24 03:27:48 +0000 2012","favourites_count":7887,"utc_offset":-25200,"time_zone":"Arizona","geo_enabled":true,"verified":false,"statuses_count":13183,"lang":"en","contributors_enabled":false,"is_translator":false,"is_translation_enabled":false,"profile_background_color":"1A1B1F","profile_background_image_url":"http:\/\/abs.twimg.com\/images\/themes\/theme9\/bg.gif","profile_background_image_url_https":"https:\/\/abs.twimg.com\/images\/themes\/theme9\/bg.gif","profile_background_tile":false,"profile_image_url":"http:\/\/pbs.twimg.com\/profile_images\/609458543876419584\/F7s92-TX_normal.jpg","profile_image_url_https":"https:\/\/pbs.twimg.com\/profile_images\/609458543876419584\/F7s92-TX_normal.jpg","profile_banner_url":"https:\/\/pbs.twimg.com\/profile_banners\/472598976\/1432713082","profile_link_color":"2FC2EF","profile_sidebar_border_color":"000000","profile_sidebar_fill_color":"252429","profile_text_color":"666666","profile_use_background_image":true,"default_profile":false,"default_profile_image":false,"following":null,"follow_request_sent":null,"notifications":null},"geo":null,"coordinates":null,"place":null,"contributors":null,"is_quote_status":false,"retweet_count":0,"favorite_count":2,"entities":{"hashtags":[],"symbols":[],"user_mentions":[],"urls":[]},"favorited":false,"retweeted":false,"lang":"en"},{"metadata":{"iso_language_code":"und","result_type":"recent"},"created_at":"Fri Jun 12 20:14:28 +0000 2015","id":609453736092692480,"id_str":"609453736092692480","text":"#justin #bieber #bieberfever #TagsForLikes #TFLers #beiber #belieberfever #justinbieberswag #hot\u2026 https:\/\/t.co\/BO5bnGHQQ8","source":"\u003ca href=\"http:\/\/instagram.com\" rel=\"nofollow\"\u003eInstagram\u003c\/a\u003e","truncated":false,"in_reply_to_status_id":null,"in_reply_to_status_id_str":null,"in_reply_to_user_id":null,"in_reply_to_user_id_str":null,"in_reply_to_screen_name":null,"user":{"id":1407362449,"id_str":"1407362449","name":"FOLLOW ME JUSTIN\u2665","screen_name":"belieber8988","location":"","description":"@justinbieber follow me please!!!!I love u!!!It's my dream!!!!U are my Idol!!!! \u2665 @gustavoelis Te amo s\u00edgueme por favor \u2665","url":null,"entities":{"description":{"urls":[]}},"protected":false,"followers_count":1125,"friends_count":1996,"listed_count":6,"created_at":"Mon May 06 10:06:01 +0000 2013","favourites_count":20170,"utc_offset":10800,"time_zone":"Athens","geo_enabled":false,"verified":false,"statuses_count":17700,"lang":"it","contributors_enabled":false,"is_translator":false,"is_translation_enabled":false,"profile_background_color":"7308D6","profile_background_image_url":"http:\/\/pbs.twimg.com\/profile_background_images\/378800000012950223\/e5d5c34faf12b93b264db62d026649f9.jpeg","profile_background_image_url_https":"https:\/\/pbs.twimg.com\/profile_background_images\/378800000012950223\/e5d5c34faf12b93b264db62d026649f9.jpeg","profile_background_tile":true,"profile_image_url":"http:\/\/pbs.twimg.com\/profile_images\/567763943519961088\/WWw8taEN_normal.jpeg","profile_image_url_https":"https:\/\/pbs.twimg.com\/profile_images\/567763943519961088\/WWw8taEN_normal.jpeg","profile_banner_url":"https:\/\/pbs.twimg.com\/profile_banners\/1407362449\/1378827336","profile_link_color":"5200CC","profile_sidebar_border_color":"FFFFFF","profile_sidebar_fill_color":"DDEEF6","profile_text_color":"333333","profile_use_background_image":true,"default_profile":false,"default_profile_image":false,"following":null,"follow_request_sent":null,"notifications":null},"geo":null,"coordinates":null,"place":null,"contributors":null,"is_quote_status":false,"retweet_count":0,"favorite_count":0,"entities":{"hashtags":[{"text":"justin","indices":[0,7]},{"text":"bieber","indices":[8,15]},{"text":"bieberfever","indices":[16,28]},{"text":"TagsForLikes","indices":[29,42]},{"text":"TFLers","indices":[43,50]},{"text":"beiber","indices":[51,58]},{"text":"belieberfever","indices":[59,73]},{"text":"justinbieberswag","indices":[74,91]},{"text":"hot","indices":[92,96]}],"symbols":[],"user_mentions":[],"urls":[{"url":"https:\/\/t.co\/BO5bnGHQQ8","expanded_url":"https:\/\/instagram.com\/p\/315Vf-KKFO\/","display_url":"instagram.com\/p\/315Vf-KKFO\/","indices":[98,121]}]},"favorited":false,"retweeted":false,"possibly_sensitive":false,"lang":"und"},{"metadata":{"iso_language_code":"en","result_type":"recent"},"created_at":"Fri Jun 12 20:14:18 +0000 2015","id":609453695986569216,"id_str":"609453695986569216","text":"Cocaine white like justin beiber bitch I might show her racks to tease the bitch I might want her but I don't need the bitch","source":"\u003ca href=\"http:\/\/www.echofon.com\/\" rel=\"nofollow\"\u003eEchofon\u003c\/a\u003e","truncated":false,"in_reply_to_status_id":null,"in_reply_to_status_id_str":null,"in_reply_to_user_id":null,"in_reply_to_user_id_str":null,"in_reply_to_screen_name":null,"user":{"id":202806413,"id_str":"202806413","name":"John Gotti","screen_name":"El_Swaveo","location":"NY\/NJ\/Chi","description":"ig: el_swaveo","url":null,"entities":{"description":{"urls":[]}},"protected":false,"followers_count":337,"friends_count":316,"listed_count":1,"created_at":"Thu Oct 14 21:31:51 +0000 2010","favourites_count":51,"utc_offset":-18000,"time_zone":"Quito","geo_enabled":true,"verified":false,"statuses_count":33701,"lang":"en","contributors_enabled":false,"is_translator":false,"is_translation_enabled":false,"profile_background_color":"6874E6","profile_background_image_url":"http:\/\/pbs.twimg.com\/profile_background_images\/380948858\/KiD-CuDi-Wallpaper-kid-cudi-7979004-800-600.jpg","profile_background_image_url_https":"https:\/\/pbs.twimg.com\/profile_background_images\/380948858\/KiD-CuDi-Wallpaper-kid-cudi-7979004-800-600.jpg","profile_background_tile":false,"profile_image_url":"http:\/\/pbs.twimg.com\/profile_images\/598324043033378816\/GhboTFHC_normal.jpg","profile_image_url_https":"https:\/\/pbs.twimg.com\/profile_images\/598324043033378816\/GhboTFHC_normal.jpg","profile_banner_url":"https:\/\/pbs.twimg.com\/profile_banners\/202806413\/1428381480","profile_link_color":"15DBB3","profile_sidebar_border_color":"0F0870","profile_sidebar_fill_color":"053E4F","profile_text_color":"F5F5F5","profile_use_background_image":true,"default_profile":false,"default_profile_image":false,"following":null,"follow_request_sent":null,"notifications":null},"geo":null,"coordinates":null,"place":null,"contributors":null,"is_quote_status":false,"retweet_count":0,"favorite_count":0,"entities":{"hashtags":[],"symbols":[],"user_mentions":[],"urls":[]},"favorited":false,"retweeted":false,"lang":"en"},{"metadata":{"iso_language_code":"en","result_type":"recent"},"created_at":"Fri Jun 12 20:13:46 +0000 2015","id":609453559512465408,"id_str":"609453559512465408","text":"I trade solo dms for ffs\nI'll trade\nNiall\nLouis\nZayn\nLiam\nFifth harmony\/Dinah j\nLauren j\nShawn mendes\nJustin Beiber \nAndrea russet","source":"\u003ca href=\"http:\/\/twitter.com\/download\/iphone\" rel=\"nofollow\"\u003eTwitter for iPhone\u003c\/a\u003e","truncated":false,"in_reply_to_status_id":null,"in_reply_to_status_id_str":null,"in_reply_to_user_id":null,"in_reply_to_user_id_str":null,"in_reply_to_screen_name":null,"user":{"id":3005572691,"id_str":"3005572691","name":"Bri \u0f04\u00b0\u25cc\u030a","screen_name":"94kindsoul","location":"otra metlife ","description":"\u2800\u2800\u2800\u2800\u2800\u2800\u2800\u2800\u201cI hope you never have to think \u2800\u2800\u2800\u2800\u2800\u2800\u2800\u2800 about anything as much as I \u2800\u2800\u2800\u2800\u2800\u2800\u2800 \u2800think about you\u201d\u2014\u13bb*\u2665\ufe0e \u2800\u2800\u2800\u2800\u2800\u2800\u2800\u2800\u2800\u2800\u2800\u2800","url":"https:\/\/t.co\/o1Dmhz8EWy","entities":{"url":{"urls":[{"url":"https:\/\/t.co\/o1Dmhz8EWy","expanded_url":"https:\/\/twitter.com\/94kindsoul\/status\/604040516565614592","display_url":"twitter.com\/94kindsoul\/sta\u2026","indices":[0,23]}]},"description":{"urls":[]}},"protected":false,"followers_count":12181,"friends_count":1799,"listed_count":17,"created_at":"Fri Jan 30 13:34:07 +0000 2015","favourites_count":7434,"utc_offset":null,"time_zone":null,"geo_enabled":true,"verified":false,"statuses_count":15976,"lang":"en","contributors_enabled":false,"is_translator":false,"is_translation_enabled":false,"profile_background_color":"C0DEED","profile_background_image_url":"http:\/\/abs.twimg.com\/images\/themes\/theme1\/bg.png","profile_background_image_url_https":"https:\/\/abs.twimg.com\/images\/themes\/theme1\/bg.png","profile_background_tile":false,"profile_image_url":"http:\/\/pbs.twimg.com\/profile_images\/609422126827835393\/siusj7g-_normal.jpg","profile_image_url_https":"https:\/\/pbs.twimg.com\/profile_images\/609422126827835393\/siusj7g-_normal.jpg","profile_banner_url":"https:\/\/pbs.twimg.com\/profile_banners\/3005572691\/1434132543","profile_link_color":"0084B4","profile_sidebar_border_color":"C0DEED","profile_sidebar_fill_color":"DDEEF6","profile_text_color":"333333","profile_use_background_image":true,"default_profile":true,"default_profile_image":false,"following":null,"follow_request_sent":null,"notifications":null},"geo":null,"coordinates":null,"place":null,"contributors":null,"is_quote_status":false,"retweet_count":0,"favorite_count":0,"entities":{"hashtags":[],"symbols":[],"user_mentions":[],"urls":[]},"favorited":false,"retweeted":false,"lang":"en"}],"search_metadata":{"completed_in":0.036,"max_id":609458378071494656,"max_id_str":"609458378071494656","next_results":"?max_id=609453559512465407&q=Justin%20Beiber&include_entities=1","query":"Justin+Beiber","refresh_url":"?since_id=609458378071494656&q=Justin%20Beiber&include_entities=1","count":15,"since_id":0,"since_id_str":"0"}}